kp.cp38-win_amd64.pyd
kompute-0.4.1.dist-info/LICENSE
kompute-0.4.1.dist-info/METADATA
kompute-0.4.1.dist-info/WHEEL
kompute-0.4.1.dist-info/top_level.txt
kompute-0.4.1.dist-info/RECORD
