Metadata-Version: 2.1
Name: kompute
Version: 0.4.1
Summary: Vulkan Kompute: Blazing fast, mobile-enabled, asynchronous, and optimized for advanced GPU processing usecases.
Home-page: UNKNOWN
Author: Alejandro Saucedo
License: UNKNOWN
Platform: UNKNOWN
